DrawScikitTree/__init__.py
DrawScikitTree/_edge.py
DrawScikitTree/_leaf.py
DrawScikitTree/_node.py
DrawScikitTree/_tree_graph.py
DrawScikitTree/py.typed
draw_scikit_tree-0.1.5.dist-info/METADATA
draw_scikit_tree-0.1.5.dist-info/WHEEL
draw_scikit_tree-0.1.5.dist-info/licenses/LICENSE
draw_scikit_tree-0.1.5.dist-info/RECORD
