Metadata-Version: 2.4
Name: draw-scikit-tree
Version: 0.1.5
Summary: A simple interface to modify scikit-learn's generated DOT representation of a decision tree.
Project-URL: GitHub, https://github.com/RenZhen95/draw-scikit-tree/
Author-email: RenZhen95 <j-liaw@hotmail.com>
License: MIT License
License-File: LICENSE
Requires-Python: >=3.13
Requires-Dist: graphviz>=0.21
Requires-Dist: matplotlib>=3.10.3
Requires-Dist: pandas>=2.3.0
Requires-Dist: scikit-learn>=1.7.0
